jsonxx/__init__.py
jsonxx/base.py
jsonxx/dictx.py
jsonxx/interface.py
jsonxx/jsonx.py
jsonxx/listx.py
jsonxx-1.1.2.dist-info/LICENSE
jsonxx-1.1.2.dist-info/METADATA
jsonxx-1.1.2.dist-info/WHEEL
jsonxx-1.1.2.dist-info/top_level.txt
jsonxx-1.1.2.dist-info/RECORD
