Metadata-Version: 2.1
Name: jsonxx
Version: 1.1.2
Summary: Python json extended.
Home-page: 
Author: SPRAVEDLIVO
Author-email: admin@spravedlivo.dev
License: AGPLv3
Classifier: Programming Language :: Python :: 3.10
Classifier: License :: OSI Approved :: GNU Affero General Public License v3 or later (AGPLv3+)
Classifier: Operating System :: OS Independent
Requires-Python: >=3.10
License-File: LICENSE
